calcmin/__init__.py
calcmin/core.py
calcmin/parameters.yml
calcmin/datasets/__init__.py
calcmin/tests/__init__.py
calcmin/tests/utest_calcmin.py
CalcMin-0.1.0.dist-info/LICENSE.txt
CalcMin-0.1.0.dist-info/METADATA
CalcMin-0.1.0.dist-info/WHEEL
CalcMin-0.1.0.dist-info/top_level.txt
CalcMin-0.1.0.dist-info/RECORD
